smith/__init__.py
smith/avaliator.py
smith/workbook_manager.py
smith/abstracts/AbstractExtractor.py
smith/abstracts/AbstractHandler.py
smith/abstracts/AbstractResult.py
smith/abstracts/__init__.py
smith/chart/__init__.py
smith/chart/bar_chart.py
smith/chart/line_chart.py
smith/singleton/Singleton.py
smith/singleton/__init__.py
smith/telegram_integration/Context.py
smith/telegram_integration/Strategy.py
smith/telegram_integration/__init__.py
smith_the_crawler-0.0.12a0.dist-info/LICENSE
smith_the_crawler-0.0.12a0.dist-info/METADATA
smith_the_crawler-0.0.12a0.dist-info/WHEEL
smith_the_crawler-0.0.12a0.dist-info/top_level.txt
smith_the_crawler-0.0.12a0.dist-info/RECORD
