Metadata-Version: 2.1
Name: smith-the-crawler
Version: 0.0.12a0
Summary: A webscraper with a sofisticated toolkit to scrap the world
Home-page: https://github.com/VictorAlessander/Smith
Author: Victor Alessander
Author-email: victor.alessander.gr@gmail.com
License: UNKNOWN
Download-URL: https://github.com/VictorAlessander/Smith/archive/refs/tags/v0.0.12-alpha.tar.gz
Keywords: crawler,webscraping,webscraper,investments,investment,invest
Platform: UNKNOWN
Classifier: Programming Language :: Python
Classifier: Programming Language :: Python :: 3.5
Classifier: Programming Language :: Python :: 3.6
Classifier: Programming Language :: Python :: 3.7
Classifier: Programming Language :: Python :: 3.8
Classifier: Programming Language :: Python :: 3 :: Only
Requires-Python: >=3.1
License-File: LICENSE
Requires-Dist: beautifulsoup4
Requires-Dist: plotly
Requires-Dist: requests
Requires-Dist: pandas
Requires-Dist: fake-useragent
Requires-Dist: openpyxl
